predict_eth/__init__.py
predict_eth/helpers.py
predict_eth/test/__init__.py
predict_eth/test/test_helpers.py
predict_eth-0.1.3.dist-info/METADATA
predict_eth-0.1.3.dist-info/WHEEL
predict_eth-0.1.3.dist-info/licenses/LICENSE
predict_eth-0.1.3.dist-info/RECORD
