Metadata-Version: 2.1
Name: predict-eth
Version: 0.1.3
Summary: Predict ETH challenges
Project-URL: Homepage, https://github.com/oceanprotocol/predict-eth
Project-URL: Bug Tracker, https://github.com/oceanprotocol/predict-eth/issues
Author-email: Trent McConaghy <gtrent@gmail.com>
License-File: LICENSE
Classifier: License :: OSI Approved :: MIT License
Classifier: Operating System :: Unix
Classifier: Programming Language :: Python :: 3
Requires-Python: >=3.8
Requires-Dist: eth-brownie>=1.19.3
Requires-Dist: matplotlib
Requires-Dist: numpy
Requires-Dist: ocean-lib
Requires-Dist: pytest
Requires-Dist: web3>=5.28.0
